langcommunity/__init__.py
langcommunity/callback/__init__.py
langcommunity/callback/displays/__init__.py
langcommunity/callback/displays/cli/__init__.py
langcommunity/callback/displays/cli/callback.py
langcommunity/callback/displays/fastapi/__init__.py
langcommunity/callback/displays/fastapi/callback.py
langcommunity/callback/displays/fastapi/models/__init__.py
langcommunity/callback/displays/fastapi/models/complete.py
langcommunity/callback/displays/fastapi/models/error.py
langcommunity/callback/displays/fastapi/models/token.py
langcommunity/callback/displays/fastapi/stream_reponse.py
langcommunity/callback/displays/llamaindex/__init__.py
langcommunity/callback/displays/llamaindex/callback.py
langcommunity/callback/displays/llamaindex/models/__init__.py
langcommunity/callback/displays/llamaindex/models/record.py
langcommunity/callback/displays/mixin/__init__.py
langcommunity/callback/displays/mixin/llamaindex/__init__.py
langcommunity/callback/displays/mixin/llamaindex/callback.py
langcommunity/callback/displays/stream_lit/__init__.py
langcommunity/callback/displays/stream_lit/callback.py
langcommunity/callback/stores/__init__.py
langcommunity/callback/stores/history/__init__.py
langcommunity/callback/stores/history/callback.py
langcommunity/history/__init__.py
langcommunity/history/memory/__init__.py
langcommunity/history/memory/conversation_summary.py
langcommunity/history/message/__init__.py
langcommunity/history/message/mangodb.py
langcommunity/services/rag/__init__.py
langcommunity/services/rag/evaluator.py
langcommunity/services/similarity/__init__.py
langcommunity/services/similarity/base.py
langcommunity/services/similarity/similarity.py
langcommunity/tools/__init__.py
langcommunity/tools/python_ast_repl_tool.py
langcommunity/tools/tools.py
langcommunity/tools/you.py
langcommunity/utils/debug/__init__.py
langcommunity/utils/debug/formatter.py
langcommunity/utils/pydantic/__init__.py
langcommunity/utils/pydantic/frozen_dict.py
langcommunity-1.2.3.dist-info/METADATA
langcommunity-1.2.3.dist-info/WHEEL
langcommunity-1.2.3.dist-info/RECORD
