Metadata-Version: 2.1
Name: langcommunity
Version: 1.2.3
Summary: langcommunity
Author: Yannick Stephan
Author-email: stephan.yannick@me.com
Requires-Python: >=3.10,<4.0
Classifier: Programming Language :: Python :: 3
Classifier: Programming Language :: Python :: 3.10
Classifier: Programming Language :: Python :: 3.11
Classifier: Programming Language :: Python :: 3.12
Requires-Dist: langfoundation
Requires-Dist: rich (>=13.7.1,<14.0.0)
Requires-Dist: strenum (>=0.4.15,<0.5.0)
